midas/__init__.py
midas/parameters.py
midas/posterior.py
midas/state.py
midas/transforms.py
midas/likelihoods/__init__.py
midas/likelihoods/uncertainties.py
midas/models/__init__.py
midas/models/diagnostics.py
midas/models/fields.py
midas/priors/__init__.py
midas/priors/base.py
midas/priors/beta.py
midas/priors/exponential.py
midas/priors/gaussian.py
midas/priors/gp.py
midas_fusion-0.3.0.dist-info/licenses/LICENSE
midas_fusion-0.3.0.dist-info/METADATA
midas_fusion-0.3.0.dist-info/WHEEL
midas_fusion-0.3.0.dist-info/top_level.txt
midas_fusion-0.3.0.dist-info/RECORD
