Metadata-Version: 2.4
Name: midas-fusion
Version: 0.3.0
Summary: A Multi-Instrument Data Analysis System for Bayesian and integrated data analysis
Author-email: Chris Bowman <chris.bowman.physics@gmail.com>
License: MIT License
Project-URL: homepage, https://github.com/C-bowman/midas
Classifier: Programming Language :: Python :: 3
Classifier: License :: OSI Approved :: MIT License
Classifier: Operating System :: OS Independent
Requires-Python: >=3.10
License-File: LICENSE
Requires-Dist: numpy>=1.26.4
Requires-Dist: scipy>=1.12
Requires-Dist: inference-tools>=0.14.2
Provides-Extra: tests
Requires-Dist: pytest>=8.0.0; extra == "tests"
Dynamic: license-file
